pandas_signals/__init__.py
pandas_signals/core.py
pandas_signals-1.0.5.dist-info/METADATA
pandas_signals-1.0.5.dist-info/WHEEL
pandas_signals-1.0.5.dist-info/top_level.txt
pandas_signals-1.0.5.dist-info/RECORD
